[
  {
    "key": "rsi_crossover|JNJ|{\"exit_level\": 45, \"fast_len\": 14, \"regime_bull\": 65, \"regime_len\": 30, \"slow_len\": 21}",
    "ticker": "JNJ",
    "strategy": "rsi_crossover",
    "sharpe": 2.1822910182862096,
    "return": 0.34135480593509737,
    "max_dd": -0.054012602866069015,
    "trades": 28,
    "score": 2.442654448731927,
    "win_rate": 1.0,
    "calmar": 4.4169574667260605,
    "sortino": 3.858362699344951,
    "profit_factor": 999.0,
    "params": {
      "fast_len": 14,
      "slow_len": 21,
      "regime_len": 30,
      "regime_bull": 65,
      "exit_level": 45
    },
    "discovered": "2026-04-26T00:51:02.024325"
  },
  {
    "key": "rsi_crossover|JNJ|{\"exit_level\": 40, \"fast_len\": 14, \"regime_bull\": 60, \"regime_len\": 50, \"slow_len\": 21}",
    "ticker": "JNJ",
    "strategy": "rsi_crossover",
    "sharpe": 2.0536493078927998,
    "return": 0.3366246917824168,
    "max_dd": -0.05734850501190092,
    "trades": 29,
    "score": 2.331102901296849,
    "win_rate": 1.0,
    "calmar": 4.104515282973001,
    "sortino": 3.548543945955551,
    "profit_factor": 999.0,
    "params": {
      "fast_len": 14,
      "slow_len": 21,
      "regime_len": 50,
      "regime_bull": 60,
      "exit_level": 40
    },
    "discovered": "2026-04-26T00:51:02.026982"
  },
  {
    "key": "rsi_crossover|JNJ|{\"exit_level\": 40, \"fast_len\": 14, \"regime_bull\": 65, \"regime_len\": 30, \"slow_len\": 21}",
    "ticker": "JNJ",
    "strategy": "rsi_crossover",
    "sharpe": 2.0536493078927998,
    "return": 0.3366246917824168,
    "max_dd": -0.05734850501190092,
    "trades": 28,
    "score": 2.290558888434244,
    "win_rate": 1.0,
    "calmar": 4.104515282973001,
    "sortino": 3.548543945955551,
    "profit_factor": 999.0,
    "params": {
      "fast_len": 14,
      "slow_len": 21,
      "regime_len": 30,
      "regime_bull": 65,
      "exit_level": 40
    },
    "discovered": "2026-04-26T00:51:02.023009"
  },
  {
    "key": "rsi_crossover|JNJ|{\"exit_level\": 50, \"fast_len\": 3, \"regime_bull\": 55, \"regime_len\": 30, \"slow_len\": 35}",
    "ticker": "JNJ",
    "strategy": "rsi_crossover",
    "sharpe": 1.992331354902743,
    "return": 0.3878114491505513,
    "max_dd": -0.09352683945539175,
    "trades": 32,
    "score": 2.284422930824675,
    "win_rate": 0.47619047619047616,
    "calmar": 2.8834370506071028,
    "sortino": 2.7910458327614256,
    "profit_factor": 3.1278118737392697,
    "params": {
      "fast_len": 3,
      "slow_len": 35,
      "regime_len": 30,
      "regime_bull": 55,
      "exit_level": 50
    },
    "discovered": "2026-04-26T00:51:01.751569"
  },
  {
    "key": "rsi_crossover|JNJ|{\"exit_level\": 45, \"fast_len\": 14, \"regime_bull\": 60, \"regime_len\": 30, \"slow_len\": 28}",
    "ticker": "JNJ",
    "strategy": "rsi_crossover",
    "sharpe": 1.858836149205271,
    "return": 0.2874494547944044,
    "max_dd": -0.057436363187438944,
    "trades": 34,
    "score": 2.2844215661873544,
    "win_rate": 0.5,
    "calmar": 3.5187998830771754,
    "sortino": 3.2069243613861906,
    "profit_factor": 8.15275384526402,
    "params": {
      "fast_len": 14,
      "slow_len": 28,
      "regime_len": 30,
      "regime_bull": 60,
      "exit_level": 45
    },
    "discovered": "2026-04-26T00:51:02.041774"
  },
  {
    "key": "rsi_crossover|JNJ|{\"exit_level\": 35, \"fast_len\": 5, \"regime_bull\": 55, \"regime_len\": 70, \"slow_len\": 14}",
    "ticker": "JNJ",
    "strategy": "rsi_crossover",
    "sharpe": 1.8822793362743462,
    "return": 0.2992365431615597,
    "max_dd": -0.0834370337823378,
    "trades": 31,
    "score": 2.147890955342347,
    "win_rate": 0.4444444444444444,
    "calmar": 2.5182498927045325,
    "sortino": 3.1357466487444086,
    "profit_factor": 4.105866377173646,
    "params": {
      "fast_len": 5,
      "slow_len": 14,
      "regime_len": 70,
      "regime_bull": 55,
      "exit_level": 35
    },
    "discovered": "2026-04-26T00:51:01.838149"
  },
  {
    "key": "rsi_crossover|JNJ|{\"exit_level\": 40, \"fast_len\": 3, \"regime_bull\": 55, \"regime_len\": 100, \"slow_len\": 35}",
    "ticker": "JNJ",
    "strategy": "rsi_crossover",
    "sharpe": 2.3648226886202695,
    "return": 0.2836214003609323,
    "max_dd": -0.04607374120599406,
    "trades": 18,
    "score": 2.1401028332976297,
    "win_rate": 0.5454545454545454,
    "calmar": 4.330058277732857,
    "sortino": 4.476059450426175,
    "profit_factor": 4.4962329602954005,
    "params": {
      "fast_len": 3,
      "slow_len": 35,
      "regime_len": 100,
      "regime_bull": 55,
      "exit_level": 40
    },
    "discovered": "2026-04-26T00:51:01.778016"
  },
  {
    "key": "rsi_crossover|JNJ|{\"exit_level\": 40, \"fast_len\": 3, \"regime_bull\": 55, \"regime_len\": 100, \"slow_len\": 42}",
    "ticker": "JNJ",
    "strategy": "rsi_crossover",
    "sharpe": 2.3648226886202695,
    "return": 0.2836214003609323,
    "max_dd": -0.04607374120599406,
    "trades": 18,
    "score": 2.1401028332976297,
    "win_rate": 0.5454545454545454,
    "calmar": 4.330058277732857,
    "sortino": 4.476059450426175,
    "profit_factor": 4.4962329602954005,
    "params": {
      "fast_len": 3,
      "slow_len": 42,
      "regime_len": 100,
      "regime_bull": 55,
      "exit_level": 40
    },
    "discovered": "2026-04-26T00:51:01.811917"
  },
  {
    "key": "rsi_crossover|JNJ|{\"exit_level\": 40, \"fast_len\": 14, \"regime_bull\": 60, \"regime_len\": 30, \"slow_len\": 21}",
    "ticker": "JNJ",
    "strategy": "rsi_crossover",
    "sharpe": 1.69607265581806,
    "return": 0.27726847220274287,
    "max_dd": -0.06496371207216078,
    "trades": 36,
    "score": 2.1276940094530463,
    "win_rate": 0.5,
    "calmar": 3.004354233307041,
    "sortino": 2.839453792413792,
    "profit_factor": 7.243724563716713,
    "params": {
      "fast_len": 14,
      "slow_len": 21,
      "regime_len": 30,
      "regime_bull": 60,
      "exit_level": 40
    },
    "discovered": "2026-04-26T00:51:02.018916"
  },
  {
    "key": "rsi_crossover|JNJ|{\"exit_level\": 30, \"fast_len\": 14, \"regime_bull\": 60, \"regime_len\": 50, \"slow_len\": 28}",
    "ticker": "JNJ",
    "strategy": "rsi_crossover",
    "sharpe": 1.7674895444812382,
    "return": 0.2888678001264793,
    "max_dd": -0.09102894320238619,
    "trades": 35,
    "score": 2.1253278467347148,
    "win_rate": 1.0,
    "calmar": 2.230848180124001,
    "sortino": 2.947322319499658,
    "profit_factor": 999.0,
    "params": {
      "fast_len": 14,
      "slow_len": 28,
      "regime_len": 50,
      "regime_bull": 60,
      "exit_level": 30
    },
    "discovered": "2026-04-26T00:51:02.043210"
  },
  {
    "key": "rsi_crossover|JNJ|{\"exit_level\": 30, \"fast_len\": 10, \"regime_bull\": 60, \"regime_len\": 50, \"slow_len\": 14}",
    "ticker": "JNJ",
    "strategy": "rsi_crossover",
    "sharpe": 1.866068382197912,
    "return": 0.30299033465537256,
    "max_dd": -0.07282219704464721,
    "trades": 30,
    "score": 2.1190256311971747,
    "win_rate": 1.0,
    "calmar": 2.92028415526286,
    "sortino": 3.1786549532536528,
    "profit_factor": 999.0,
    "params": {
      "fast_len": 10,
      "slow_len": 14,
      "regime_len": 50,
      "regime_bull": 60,
      "exit_level": 30
    },
    "discovered": "2026-04-26T00:51:01.985253"
  },
  {
    "key": "rsi_crossover|JNJ|{\"exit_level\": 30, \"fast_len\": 10, \"regime_bull\": 55, \"regime_len\": 100, \"slow_len\": 42}",
    "ticker": "JNJ",
    "strategy": "rsi_crossover",
    "sharpe": 1.9253197509121354,
    "return": 0.3146839014118817,
    "max_dd": -0.0728221970446471,
    "trades": 28,
    "score": 2.1121750575706226,
    "win_rate": 1.0,
    "calmar": 3.029029189376624,
    "sortino": 3.2831097840953656,
    "profit_factor": 999.0,
    "params": {
      "fast_len": 10,
      "slow_len": 42,
      "regime_len": 100,
      "regime_bull": 55,
      "exit_level": 30
    },
    "discovered": "2026-04-26T00:51:02.015963"
  },
  {
    "key": "rsi_crossover|JNJ|{\"exit_level\": 35, \"fast_len\": 14, \"regime_bull\": 65, \"regime_len\": 30, \"slow_len\": 21}",
    "ticker": "JNJ",
    "strategy": "rsi_crossover",
    "sharpe": 1.9253197509121354,
    "return": 0.3146839014118817,
    "max_dd": -0.0728221970446471,
    "trades": 28,
    "score": 2.1121750575706226,
    "win_rate": 1.0,
    "calmar": 3.029029189376624,
    "sortino": 3.2831097840953656,
    "profit_factor": 999.0,
    "params": {
      "fast_len": 14,
      "slow_len": 21,
      "regime_len": 30,
      "regime_bull": 65,
      "exit_level": 35
    },
    "discovered": "2026-04-26T00:51:02.021659"
  },
  {
    "key": "rsi_crossover|JNJ|{\"exit_level\": 45, \"fast_len\": 14, \"regime_bull\": 60, \"regime_len\": 50, \"slow_len\": 21}",
    "ticker": "JNJ",
    "strategy": "rsi_crossover",
    "sharpe": 1.806980031069116,
    "return": 0.28445741254385926,
    "max_dd": -0.09413935891877523,
    "trades": 33,
    "score": 2.102600268942205,
    "win_rate": 0.5,
    "calmar": 2.1252650653404457,
    "sortino": 3.0674859343075087,
    "profit_factor": 5.999480566497517,
    "params": {
      "fast_len": 14,
      "slow_len": 21,
      "regime_len": 50,
      "regime_bull": 60,
      "exit_level": 45
    },
    "discovered": "2026-04-26T00:51:02.028240"
  },
  {
    "key": "rsi_crossover|JNJ|{\"exit_level\": 40, \"fast_len\": 5, \"regime_bull\": 60, \"regime_len\": 30, \"slow_len\": 35}",
    "ticker": "JNJ",
    "strategy": "rsi_crossover",
    "sharpe": 1.84217484270469,
    "return": 0.24108234531742592,
    "max_dd": -0.04737126568774097,
    "trades": 28,
    "score": 2.0764359629844984,
    "win_rate": 0.5,
    "calmar": 3.597313454007378,
    "sortino": 3.0412271549798,
    "profit_factor": 7.250112066057982,
    "params": {
      "fast_len": 5,
      "slow_len": 35,
      "regime_len": 30,
      "regime_bull": 60,
      "exit_level": 40
    },
    "discovered": "2026-04-26T00:51:01.890872"
  },
  {
    "key": "rsi_crossover|JNJ|{\"exit_level\": 50, \"fast_len\": 3, \"regime_bull\": 55, \"regime_len\": 70, \"slow_len\": 42}",
    "ticker": "JNJ",
    "strategy": "rsi_crossover",
    "sharpe": 2.8099354363009112,
    "return": 0.3747424144373472,
    "max_dd": -0.04607374120599417,
    "trades": 12,
    "score": 2.076284062125951,
    "win_rate": 0.5714285714285714,
    "calmar": 5.663892026576312,
    "sortino": 5.431315658844644,
    "profit_factor": 5.715813171334902,
    "params": {
      "fast_len": 3,
      "slow_len": 42,
      "regime_len": 70,
      "regime_bull": 55,
      "exit_level": 50
    },
    "discovered": "2026-04-26T00:51:01.800016"
  },
  {
    "key": "rsi_crossover|JNJ|{\"exit_level\": 50, \"fast_len\": 5, \"regime_bull\": 55, \"regime_len\": 100, \"slow_len\": 35}",
    "ticker": "JNJ",
    "strategy": "rsi_crossover",
    "sharpe": 2.752810764699267,
    "return": 0.3172190109523067,
    "max_dd": -0.029304765921991383,
    "trades": 12,
    "score": 2.069830968079596,
    "win_rate": 0.8333333333333334,
    "calmar": 7.585620970035244,
    "sortino": 5.440210849277726,
    "profit_factor": 39.85931580153183,
    "params": {
      "fast_len": 5,
      "slow_len": 35,
      "regime_len": 100,
      "regime_bull": 55,
      "exit_level": 50
    },
    "discovered": "2026-04-26T00:51:01.911536"
  },
  {
    "key": "rsi_crossover|JNJ|{\"exit_level\": 40, \"fast_len\": 5, \"regime_bull\": 55, \"regime_len\": 70, \"slow_len\": 35}",
    "ticker": "JNJ",
    "strategy": "rsi_crossover",
    "sharpe": 2.3151644632693267,
    "return": 0.33281309540409637,
    "max_dd": -0.044904512345490866,
    "trades": 17,
    "score": 2.038628558000897,
    "win_rate": 0.5714285714285714,
    "calmar": 5.184784828415939,
    "sortino": 3.960645622686945,
    "profit_factor": 9.804450022129545,
    "params": {
      "fast_len": 5,
      "slow_len": 35,
      "regime_len": 70,
      "regime_bull": 55,
      "exit_level": 40
    },
    "discovered": "2026-04-26T00:51:01.900368"
  },
  {
    "key": "roc_ema_volume|CAT|{\"atr_len\": 14, \"atr_mult\": 1.5, \"ema_len\": 15, \"roc_len\": 8, \"trailing_len\": 10, \"vol_sma_len\": 15}",
    "ticker": "CAT",
    "strategy": "roc_ema_volume",
    "sharpe": 2.6576223219722452,
    "return": 1.5999390361426409,
    "max_dd": -0.12306584314143265,
    "trades": 15,
    "score": 2.0183239833233593,
    "win_rate": 0.5333333333333333,
    "calmar": 8.174018425729765,
    "sortino": 4.895178771311496,
    "profit_factor": 9.687821930248566,
    "params": {
      "roc_len": 8,
      "ema_len": 15,
      "vol_sma_len": 15,
      "atr_len": 14,
      "atr_mult": 1.5,
      "trailing_len": 10
    },
    "discovered": "2026-04-25T21:07:54.764063"
  },
  {
    "key": "roc_ema_volume|CAT|{\"atr_len\": 10, \"atr_mult\": 1.5, \"ema_len\": 15, \"roc_len\": 8, \"trailing_len\": 10, \"vol_sma_len\": 15}",
    "ticker": "CAT",
    "strategy": "roc_ema_volume",
    "sharpe": 2.7493479848756865,
    "return": 1.6991306266635575,
    "max_dd": -0.12306584314143265,
    "trades": 14,
    "score": 2.0171849453724273,
    "win_rate": 0.5,
    "calmar": 8.624761248876284,
    "sortino": 5.0675110277809505,
    "profit_factor": 10.226441750102142,
    "params": {
      "roc_len": 8,
      "ema_len": 15,
      "vol_sma_len": 15,
      "atr_len": 10,
      "atr_mult": 1.5,
      "trailing_len": 10
    },
    "discovered": "2026-04-25T21:07:54.742202"
  },
  {
    "key": "roc_ema_volume|CAT|{\"atr_len\": 14, \"atr_mult\": 1.5, \"ema_len\": 25, \"roc_len\": 8, \"trailing_len\": 10, \"vol_sma_len\": 15}",
    "ticker": "CAT",
    "strategy": "roc_ema_volume",
    "sharpe": 2.8234848232648933,
    "return": 1.7435755834909485,
    "max_dd": -0.12227207143830254,
    "trades": 13,
    "score": 1.9980302239186665,
    "win_rate": 0.6153846153846154,
    "calmar": 8.882554406728127,
    "sortino": 5.250201260364291,
    "profit_factor": 14.644912843945015,
    "params": {
      "roc_len": 8,
      "ema_len": 25,
      "vol_sma_len": 15,
      "atr_len": 14,
      "atr_mult": 1.5,
      "trailing_len": 10
    },
    "discovered": "2026-04-25T21:07:55.006365"
  },
  {
    "key": "roc_ema_volume|CAT|{\"atr_len\": 14, \"atr_mult\": 1.5, \"ema_len\": 25, \"roc_len\": 8, \"trailing_len\": 10, \"vol_sma_len\": 20}",
    "ticker": "CAT",
    "strategy": "roc_ema_volume",
    "sharpe": 2.8234848232648933,
    "return": 1.7435755834909485,
    "max_dd": -0.12227207143830254,
    "trades": 13,
    "score": 1.9980302239186665,
    "win_rate": 0.6153846153846154,
    "calmar": 8.882554406728127,
    "sortino": 5.250201260364291,
    "profit_factor": 14.644912843945015,
    "params": {
      "roc_len": 8,
      "ema_len": 25,
      "vol_sma_len": 20,
      "atr_len": 14,
      "atr_mult": 1.5,
      "trailing_len": 10
    },
    "discovered": "2026-04-25T21:07:55.058973"
  },
  {
    "key": "rsi_crossover|JNJ|{\"exit_level\": 45, \"fast_len\": 14, \"regime_bull\": 55, \"regime_len\": 100, \"slow_len\": 35}",
    "ticker": "JNJ",
    "strategy": "rsi_crossover",
    "sharpe": 2.1553686638245533,
    "return": 0.33136039161767505,
    "max_dd": -0.054012602866069126,
    "trades": 19,
    "score": 1.9873241847759755,
    "win_rate": 1.0,
    "calmar": 4.292352565621671,
    "sortino": 3.8002433840277727,
    "profit_factor": 999.0,
    "params": {
      "fast_len": 14,
      "slow_len": 35,
      "regime_len": 100,
      "regime_bull": 55,
      "exit_level": 45
    },
    "discovered": "2026-04-26T00:51:02.105902"
  },
  {
    "key": "roc_ema_volume|CAT|{\"atr_len\": 10, \"atr_mult\": 1.5, \"ema_len\": 25, \"roc_len\": 8, \"trailing_len\": 10, \"vol_sma_len\": 15}",
    "ticker": "CAT",
    "strategy": "roc_ema_volume",
    "sharpe": 2.915618325650432,
    "return": 1.8482471246531516,
    "max_dd": -0.12227207143830254,
    "trades": 12,
    "score": 1.982285544260607,
    "win_rate": 0.5833333333333334,
    "calmar": 9.354349371813747,
    "sortino": 5.424760714661816,
    "profit_factor": 15.464053734608374,
    "params": {
      "roc_len": 8,
      "ema_len": 25,
      "vol_sma_len": 15,
      "atr_len": 10,
      "atr_mult": 1.5,
      "trailing_len": 10
    },
    "discovered": "2026-04-25T21:07:54.988476"
  },
  {
    "key": "roc_ema_volume|CAT|{\"atr_len\": 10, \"atr_mult\": 1.5, \"ema_len\": 25, \"roc_len\": 8, \"trailing_len\": 10, \"vol_sma_len\": 20}",
    "ticker": "CAT",
    "strategy": "roc_ema_volume",
    "sharpe": 2.915618325650432,
    "return": 1.8482471246531516,
    "max_dd": -0.12227207143830254,
    "trades": 12,
    "score": 1.982285544260607,
    "win_rate": 0.5833333333333334,
    "calmar": 9.354349371813747,
    "sortino": 5.424760714661816,
    "profit_factor": 15.464053734608374,
    "params": {
      "roc_len": 8,
      "ema_len": 25,
      "vol_sma_len": 20,
      "atr_len": 10,
      "atr_mult": 1.5,
      "trailing_len": 10
    },
    "discovered": "2026-04-25T21:07:55.040393"
  },
  {
    "key": "rsi_crossover|JNJ|{\"exit_level\": 45, \"fast_len\": 7, \"regime_bull\": 60, \"regime_len\": 30, \"slow_len\": 35}",
    "ticker": "JNJ",
    "strategy": "rsi_crossover",
    "sharpe": 1.8751804581002711,
    "return": 0.25810770431409485,
    "max_dd": -0.054987635916903255,
    "trades": 25,
    "score": 1.981233056891635,
    "win_rate": 0.5714285714285714,
    "calmar": 3.3113810700328905,
    "sortino": 3.1130178498523544,
    "profit_factor": 4.908235468088202,
    "params": {
      "fast_len": 7,
      "slow_len": 35,
      "regime_len": 30,
      "regime_bull": 60,
      "exit_level": 45
    },
    "discovered": "2026-04-26T00:51:01.972056"
  },
  {
    "key": "roc_ema_volume|CAT|{\"atr_len\": 10, \"atr_mult\": 1.5, \"ema_len\": 15, \"roc_len\": 8, \"trailing_len\": 20, \"vol_sma_len\": 15}",
    "ticker": "CAT",
    "strategy": "roc_ema_volume",
    "sharpe": 2.5455482316443687,
    "return": 1.449271691928278,
    "max_dd": -0.10553878474857603,
    "trades": 15,
    "score": 1.97184818840875,
    "win_rate": 0.5333333333333333,
    "calmar": 8.722574575653082,
    "sortino": 4.633714575759267,
    "profit_factor": 8.519611847493996,
    "params": {
      "roc_len": 8,
      "ema_len": 15,
      "vol_sma_len": 15,
      "atr_len": 10,
      "atr_mult": 1.5,
      "trailing_len": 20
    },
    "discovered": "2026-04-25T21:07:54.746818"
  },
  {
    "key": "roc_ema_volume|CAT|{\"atr_len\": 14, \"atr_mult\": 1.5, \"ema_len\": 15, \"roc_len\": 8, \"trailing_len\": 20, \"vol_sma_len\": 15}",
    "ticker": "CAT",
    "strategy": "roc_ema_volume",
    "sharpe": 2.5455482316443687,
    "return": 1.449271691928278,
    "max_dd": -0.10553878474857603,
    "trades": 15,
    "score": 1.97184818840875,
    "win_rate": 0.5333333333333333,
    "calmar": 8.722574575653082,
    "sortino": 4.633714575759267,
    "profit_factor": 8.519611847493996,
    "params": {
      "roc_len": 8,
      "ema_len": 15,
      "vol_sma_len": 15,
      "atr_len": 14,
      "atr_mult": 1.5,
      "trailing_len": 20
    },
    "discovered": "2026-04-25T21:07:54.767110"
  },
  {
    "key": "rsi_crossover|JNJ|{\"exit_level\": 35, \"fast_len\": 10, \"regime_bull\": 55, \"regime_len\": 70, \"slow_len\": 28}",
    "ticker": "JNJ",
    "strategy": "rsi_crossover",
    "sharpe": 1.6527644796316254,
    "return": 0.3330510031677771,
    "max_dd": -0.08874843882481986,
    "trades": 34,
    "score": 1.9636935638778168,
    "win_rate": 0.5,
    "calmar": 2.625179168851164,
    "sortino": 2.3615519164054914,
    "profit_factor": 5.282903341743044,
    "params": {
      "fast_len": 10,
      "slow_len": 28,
      "regime_len": 70,
      "regime_bull": 55,
      "exit_level": 35
    },
    "discovered": "2026-04-26T00:51:02.001953"
  },
  {
    "key": "roc_ema_volume|CAT|{\"atr_len\": 14, \"atr_mult\": 1.5, \"ema_len\": 15, \"roc_len\": 8, \"trailing_len\": 10, \"vol_sma_len\": 20}",
    "ticker": "CAT",
    "strategy": "roc_ema_volume",
    "sharpe": 2.674722626022358,
    "return": 1.6052929250741739,
    "max_dd": -0.12306584314143221,
    "trades": 14,
    "score": 1.9624326363704252,
    "win_rate": 0.5714285714285714,
    "calmar": 8.198465167092314,
    "sortino": 4.936945835191694,
    "profit_factor": 9.79714703428904,
    "params": {
      "roc_len": 8,
      "ema_len": 15,
      "vol_sma_len": 20,
      "atr_len": 14,
      "atr_mult": 1.5,
      "trailing_len": 10
    },
    "discovered": "2026-04-25T21:07:54.805680"
  },
  {
    "key": "roc_ema_volume|CAT|{\"atr_len\": 14, \"atr_mult\": 1.5, \"ema_len\": 20, \"roc_len\": 8, \"trailing_len\": 10, \"vol_sma_len\": 15}",
    "ticker": "CAT",
    "strategy": "roc_ema_volume",
    "sharpe": 2.674722626022358,
    "return": 1.6052929250741739,
    "max_dd": -0.12306584314143221,
    "trades": 14,
    "score": 1.9624326363704252,
    "win_rate": 0.5714285714285714,
    "calmar": 8.198465167092314,
    "sortino": 4.936945835191694,
    "profit_factor": 9.79714703428904,
    "params": {
      "roc_len": 8,
      "ema_len": 20,
      "vol_sma_len": 15,
      "atr_len": 14,
      "atr_mult": 1.5,
      "trailing_len": 10
    },
    "discovered": "2026-04-25T21:07:54.885018"
  },
  {
    "key": "roc_ema_volume|CAT|{\"atr_len\": 14, \"atr_mult\": 1.5, \"ema_len\": 20, \"roc_len\": 8, \"trailing_len\": 10, \"vol_sma_len\": 20}",
    "ticker": "CAT",
    "strategy": "roc_ema_volume",
    "sharpe": 2.674722626022358,
    "return": 1.6052929250741739,
    "max_dd": -0.12306584314143221,
    "trades": 14,
    "score": 1.9624326363704252,
    "win_rate": 0.5714285714285714,
    "calmar": 8.198465167092314,
    "sortino": 4.936945835191694,
    "profit_factor": 9.79714703428904,
    "params": {
      "roc_len": 8,
      "ema_len": 20,
      "vol_sma_len": 20,
      "atr_len": 14,
      "atr_mult": 1.5,
      "trailing_len": 10
    },
    "discovered": "2026-04-25T21:07:54.925761"
  },
  {
    "key": "roc_ema_volume|CAT|{\"atr_len\": 20, \"atr_mult\": 1.5, \"ema_len\": 25, \"roc_len\": 8, \"trailing_len\": 10, \"vol_sma_len\": 15}",
    "ticker": "CAT",
    "strategy": "roc_ema_volume",
    "sharpe": 2.6649402166166434,
    "return": 1.434162652005282,
    "max_dd": -0.12227207143830254,
    "trades": 14,
    "score": 1.9570251563625942,
    "win_rate": 0.5714285714285714,
    "calmar": 7.4582133593739215,
    "sortino": 4.628334910648305,
    "profit_factor": 6.78102253721509,
    "params": {
      "roc_len": 8,
      "ema_len": 25,
      "vol_sma_len": 15,
      "atr_len": 20,
      "atr_mult": 1.5,
      "trailing_len": 10
    },
    "discovered": "2026-04-25T21:07:55.023332"
  },
  {
    "key": "roc_ema_volume|CAT|{\"atr_len\": 20, \"atr_mult\": 1.5, \"ema_len\": 25, \"roc_len\": 8, \"trailing_len\": 10, \"vol_sma_len\": 20}",
    "ticker": "CAT",
    "strategy": "roc_ema_volume",
    "sharpe": 2.6649402166166434,
    "return": 1.434162652005282,
    "max_dd": -0.12227207143830254,
    "trades": 14,
    "score": 1.9570251563625942,
    "win_rate": 0.5714285714285714,
    "calmar": 7.4582133593739215,
    "sortino": 4.628334910648305,
    "profit_factor": 6.78102253721509,
    "params": {
      "roc_len": 8,
      "ema_len": 25,
      "vol_sma_len": 20,
      "atr_len": 20,
      "atr_mult": 1.5,
      "trailing_len": 10
    },
    "discovered": "2026-04-25T21:07:55.084898"
  },
  {
    "key": "roc_ema_volume|CAT|{\"atr_len\": 10, \"atr_mult\": 1.5, \"ema_len\": 15, \"roc_len\": 8, \"trailing_len\": 10, \"vol_sma_len\": 20}",
    "ticker": "CAT",
    "strategy": "roc_ema_volume",
    "sharpe": 2.766808915461685,
    "return": 1.7046887745224004,
    "max_dd": -0.12306584314143221,
    "trades": 13,
    "score": 1.9561530497927635,
    "win_rate": 0.5384615384615384,
    "calmar": 8.649884024733744,
    "sortino": 5.1103037546883785,
    "profit_factor": 10.34184506948016,
    "params": {
      "roc_len": 8,
      "ema_len": 15,
      "vol_sma_len": 20,
      "atr_len": 10,
      "atr_mult": 1.5,
      "trailing_len": 10
    },
    "discovered": "2026-04-25T21:07:54.791428"
  },
  {
    "key": "roc_ema_volume|CAT|{\"atr_len\": 10, \"atr_mult\": 1.5, \"ema_len\": 20, \"roc_len\": 8, \"trailing_len\": 10, \"vol_sma_len\": 15}",
    "ticker": "CAT",
    "strategy": "roc_ema_volume",
    "sharpe": 2.766808915461685,
    "return": 1.7046887745224004,
    "max_dd": -0.12306584314143221,
    "trades": 13,
    "score": 1.9561530497927635,
    "win_rate": 0.5384615384615384,
    "calmar": 8.649884024733744,
    "sortino": 5.1103037546883785,
    "profit_factor": 10.34184506948016,
    "params": {
      "roc_len": 8,
      "ema_len": 20,
      "vol_sma_len": 15,
      "atr_len": 10,
      "atr_mult": 1.5,
      "trailing_len": 10
    },
    "discovered": "2026-04-25T21:07:54.872421"
  },
  {
    "key": "roc_ema_volume|CAT|{\"atr_len\": 10, \"atr_mult\": 1.5, \"ema_len\": 20, \"roc_len\": 8, \"trailing_len\": 10, \"vol_sma_len\": 20}",
    "ticker": "CAT",
    "strategy": "roc_ema_volume",
    "sharpe": 2.766808915461685,
    "return": 1.7046887745224004,
    "max_dd": -0.12306584314143221,
    "trades": 13,
    "score": 1.9561530497927635,
    "win_rate": 0.5384615384615384,
    "calmar": 8.649884024733744,
    "sortino": 5.1103037546883785,
    "profit_factor": 10.34184506948016,
    "params": {
      "roc_len": 8,
      "ema_len": 20,
      "vol_sma_len": 20,
      "atr_len": 10,
      "atr_mult": 1.5,
      "trailing_len": 10
    },
    "discovered": "2026-04-25T21:07:54.912594"
  },
  {
    "key": "roc_ema_volume|CAT|{\"atr_len\": 10, \"atr_mult\": 1.5, \"ema_len\": 20, \"roc_len\": 8, \"trailing_len\": 20, \"vol_sma_len\": 15}",
    "ticker": "CAT",
    "strategy": "roc_ema_volume",
    "sharpe": 2.609396893036032,
    "return": 1.4936108798153098,
    "max_dd": -0.10553878474857536,
    "trades": 14,
    "score": 1.9527681129705188,
    "win_rate": 0.5714285714285714,
    "calmar": 8.961996353608034,
    "sortino": 4.772029562109383,
    "profit_factor": 9.549982224249947,
    "params": {
      "roc_len": 8,
      "ema_len": 20,
      "vol_sma_len": 15,
      "atr_len": 10,
      "atr_mult": 1.5,
      "trailing_len": 20
    },
    "discovered": "2026-04-25T21:07:54.875135"
  },
  {
    "key": "roc_ema_volume|CAT|{\"atr_len\": 14, \"atr_mult\": 1.5, \"ema_len\": 20, \"roc_len\": 8, \"trailing_len\": 20, \"vol_sma_len\": 15}",
    "ticker": "CAT",
    "strategy": "roc_ema_volume",
    "sharpe": 2.609396893036032,
    "return": 1.4936108798153098,
    "max_dd": -0.10553878474857536,
    "trades": 14,
    "score": 1.9527681129705188,
    "win_rate": 0.5714285714285714,
    "calmar": 8.961996353608034,
    "sortino": 4.772029562109383,
    "profit_factor": 9.549982224249947,
    "params": {
      "roc_len": 8,
      "ema_len": 20,
      "vol_sma_len": 15,
      "atr_len": 14,
      "atr_mult": 1.5,
      "trailing_len": 20
    },
    "discovered": "2026-04-25T21:07:54.888914"
  },
  {
    "key": "roc_ema_volume|CAT|{\"atr_len\": 10, \"atr_mult\": 1.5, \"ema_len\": 20, \"roc_len\": 8, \"trailing_len\": 20, \"vol_sma_len\": 20}",
    "ticker": "CAT",
    "strategy": "roc_ema_volume",
    "sharpe": 2.609396893036032,
    "return": 1.4936108798153098,
    "max_dd": -0.10553878474857536,
    "trades": 14,
    "score": 1.9527681129705188,
    "win_rate": 0.5714285714285714,
    "calmar": 8.961996353608034,
    "sortino": 4.772029562109383,
    "profit_factor": 9.549982224249947,
    "params": {
      "roc_len": 8,
      "ema_len": 20,
      "vol_sma_len": 20,
      "atr_len": 10,
      "atr_mult": 1.5,
      "trailing_len": 20
    },
    "discovered": "2026-04-25T21:07:54.915396"
  },
  {
    "key": "roc_ema_volume|CAT|{\"atr_len\": 14, \"atr_mult\": 1.5, \"ema_len\": 20, \"roc_len\": 8, \"trailing_len\": 20, \"vol_sma_len\": 20}",
    "ticker": "CAT",
    "strategy": "roc_ema_volume",
    "sharpe": 2.609396893036032,
    "return": 1.4936108798153098,
    "max_dd": -0.10553878474857536,
    "trades": 14,
    "score": 1.9527681129705188,
    "win_rate": 0.5714285714285714,
    "calmar": 8.961996353608034,
    "sortino": 4.772029562109383,
    "profit_factor": 9.549982224249947,
    "params": {
      "roc_len": 8,
      "ema_len": 20,
      "vol_sma_len": 20,
      "atr_len": 14,
      "atr_mult": 1.5,
      "trailing_len": 20
    },
    "discovered": "2026-04-25T21:07:54.928394"
  },
  {
    "key": "roc_ema_volume|CAT|{\"atr_len\": 20, \"atr_mult\": 1.5, \"ema_len\": 15, \"roc_len\": 8, \"trailing_len\": 10, \"vol_sma_len\": 15}",
    "ticker": "CAT",
    "strategy": "roc_ema_volume",
    "sharpe": 2.4876033660648544,
    "return": 1.3067250406188429,
    "max_dd": -0.12306584314143265,
    "trades": 16,
    "score": 1.9511610401556518,
    "win_rate": 0.5,
    "calmar": 6.813233440049872,
    "sortino": 4.284761807701186,
    "profit_factor": 5.382633917423635,
    "params": {
      "roc_len": 8,
      "ema_len": 15,
      "vol_sma_len": 15,
      "atr_len": 20,
      "atr_mult": 1.5,
      "trailing_len": 10
    },
    "discovered": "2026-04-25T21:07:54.776879"
  },
  {
    "key": "roc_ema_volume|CAT|{\"atr_len\": 10, \"atr_mult\": 1.5, \"ema_len\": 15, \"roc_len\": 8, \"trailing_len\": 15, \"vol_sma_len\": 15}",
    "ticker": "CAT",
    "strategy": "roc_ema_volume",
    "sharpe": 2.5478030800060383,
    "return": 1.4676118056636804,
    "max_dd": -0.12306584314143265,
    "trades": 15,
    "score": 1.9349220612149174,
    "win_rate": 0.5333333333333333,
    "calmar": 7.565353673984042,
    "sortino": 4.641997414816917,
    "profit_factor": 7.316544313090753,
    "params": {
      "roc_len": 8,
      "ema_len": 15,
      "vol_sma_len": 15,
      "atr_len": 10,
      "atr_mult": 1.5,
      "trailing_len": 15
    },
    "discovered": "2026-04-25T21:07:54.743699"
  },
  {
    "key": "roc_ema_volume|CAT|{\"atr_len\": 14, \"atr_mult\": 1.5, \"ema_len\": 15, \"roc_len\": 8, \"trailing_len\": 15, \"vol_sma_len\": 15}",
    "ticker": "CAT",
    "strategy": "roc_ema_volume",
    "sharpe": 2.5478030800060383,
    "return": 1.4676118056636804,
    "max_dd": -0.12306584314143265,
    "trades": 15,
    "score": 1.9349220612149174,
    "win_rate": 0.5333333333333333,
    "calmar": 7.565353673984042,
    "sortino": 4.641997414816917,
    "profit_factor": 7.316544313090753,
    "params": {
      "roc_len": 8,
      "ema_len": 15,
      "vol_sma_len": 15,
      "atr_len": 14,
      "atr_mult": 1.5,
      "trailing_len": 15
    },
    "discovered": "2026-04-25T21:07:54.765432"
  },
  {
    "key": "rsi_crossover|JNJ|{\"exit_level\": 30, \"fast_len\": 14, \"regime_bull\": 55, \"regime_len\": 100, \"slow_len\": 42}",
    "ticker": "JNJ",
    "strategy": "rsi_crossover",
    "sharpe": 1.7357926007047124,
    "return": 0.2792644656933734,
    "max_dd": -0.09102894320238575,
    "trades": 30,
    "score": 1.9323843742876647,
    "win_rate": 1.0,
    "calmar": 2.1590321782522777,
    "sortino": 2.8845079988035134,
    "profit_factor": 999.0,
    "params": {
      "fast_len": 14,
      "slow_len": 42,
      "regime_len": 100,
      "regime_bull": 55,
      "exit_level": 30
    },
    "discovered": "2026-04-26T00:51:02.127975"
  },
  {
    "key": "roc_ema_volume|CAT|{\"atr_len\": 14, \"atr_mult\": 1.5, \"ema_len\": 15, \"roc_len\": 12, \"trailing_len\": 10, \"vol_sma_len\": 15}",
    "ticker": "CAT",
    "strategy": "roc_ema_volume",
    "sharpe": 2.6516617306913983,
    "return": 1.5278659885406243,
    "max_dd": -0.09765359288993714,
    "trades": 13,
    "score": 1.9290704684337763,
    "win_rate": 0.6153846153846154,
    "calmar": 9.884697799229267,
    "sortino": 4.837774925538048,
    "profit_factor": 12.127121966000482,
    "params": {
      "roc_len": 12,
      "ema_len": 15,
      "vol_sma_len": 15,
      "atr_len": 14,
      "atr_mult": 1.5,
      "trailing_len": 10
    },
    "discovered": "2026-04-25T21:07:55.665263"
  },
  {
    "key": "roc_ema_volume|CAT|{\"atr_len\": 10, \"atr_mult\": 1.5, \"ema_len\": 25, \"roc_len\": 8, \"trailing_len\": 15, \"vol_sma_len\": 15}",
    "ticker": "CAT",
    "strategy": "roc_ema_volume",
    "sharpe": 2.7148879194128273,
    "return": 1.6039377867864213,
    "max_dd": -0.12227207143830254,
    "trades": 13,
    "score": 1.9211819638067116,
    "win_rate": 0.6153846153846154,
    "calmar": 8.245461699862389,
    "sortino": 4.992899140270201,
    "profit_factor": 9.979135234136113,
    "params": {
      "roc_len": 8,
      "ema_len": 25,
      "vol_sma_len": 15,
      "atr_len": 10,
      "atr_mult": 1.5,
      "trailing_len": 15
    },
    "discovered": "2026-04-25T21:07:54.989714"
  },
  {
    "key": "roc_ema_volume|CAT|{\"atr_len\": 14, \"atr_mult\": 1.5, \"ema_len\": 25, \"roc_len\": 8, \"trailing_len\": 15, \"vol_sma_len\": 15}",
    "ticker": "CAT",
    "strategy": "roc_ema_volume",
    "sharpe": 2.7148879194128273,
    "return": 1.6039377867864213,
    "max_dd": -0.12227207143830254,
    "trades": 13,
    "score": 1.9211819638067116,
    "win_rate": 0.6153846153846154,
    "calmar": 8.245461699862389,
    "sortino": 4.992899140270201,
    "profit_factor": 9.979135234136113,
    "params": {
      "roc_len": 8,
      "ema_len": 25,
      "vol_sma_len": 15,
      "atr_len": 14,
      "atr_mult": 1.5,
      "trailing_len": 15
    },
    "discovered": "2026-04-25T21:07:55.007659"
  },
  {
    "key": "roc_ema_volume|CAT|{\"atr_len\": 10, \"atr_mult\": 1.5, \"ema_len\": 25, \"roc_len\": 8, \"trailing_len\": 15, \"vol_sma_len\": 20}",
    "ticker": "CAT",
    "strategy": "roc_ema_volume",
    "sharpe": 2.7148879194128273,
    "return": 1.6039377867864213,
    "max_dd": -0.12227207143830254,
    "trades": 13,
    "score": 1.9211819638067116,
    "win_rate": 0.6153846153846154,
    "calmar": 8.245461699862389,
    "sortino": 4.992899140270201,
    "profit_factor": 9.979135234136113,
    "params": {
      "roc_len": 8,
      "ema_len": 25,
      "vol_sma_len": 20,
      "atr_len": 10,
      "atr_mult": 1.5,
      "trailing_len": 15
    },
    "discovered": "2026-04-25T21:07:55.041838"
  },
  {
    "key": "roc_ema_volume|CAT|{\"atr_len\": 14, \"atr_mult\": 1.5, \"ema_len\": 25, \"roc_len\": 8, \"trailing_len\": 15, \"vol_sma_len\": 20}",
    "ticker": "CAT",
    "strategy": "roc_ema_volume",
    "sharpe": 2.7148879194128273,
    "return": 1.6039377867864213,
    "max_dd": -0.12227207143830254,
    "trades": 13,
    "score": 1.9211819638067116,
    "win_rate": 0.6153846153846154,
    "calmar": 8.245461699862389,
    "sortino": 4.992899140270201,
    "profit_factor": 9.979135234136113,
    "params": {
      "roc_len": 8,
      "ema_len": 25,
      "vol_sma_len": 20,
      "atr_len": 14,
      "atr_mult": 1.5,
      "trailing_len": 15
    },
    "discovered": "2026-04-25T21:07:55.060580"
  }
]